{
  "users": [
    {
      "id": 1,
      "name": "Meal 66",
      "description": "Its a great meal",
      "favorite": true,
      "steps": [
        "Step16",
        "step26"
      ],
      "ingredients": [
        "ingredient16",
        "ingredients26"
      ],
      "avatar": "https://z9u1l3wusky40y46t31hrkw2-wpengine.netdna-ssl.com/wp-content/uploads/2016/02/pasta9-best-swaps.jpg"
    },
    {
      "id": 2,
      "name": "Meal 66",
      "description": "Its a great meal",
      "favorite": false,
      "steps": [
        "Step16",
        "step26"
      ],
      "ingredients": [
        "ingredient16",
        "ingredients26"
      ],
      "avatar": "https://z9u1l3wusky40y46t31hrkw2-wpengine.netdna-ssl.com/wp-content/uploads/2015/07/tofu-healthy-grills-by-healthista.com_.jpg"
    },
    {
      "id": 3,
      "name": "Meal 444",
      "description": "Its a great meal",
      "favorite": false,
      "date": "Today",
      "steps": [
        "Step14",
        "step24"
      ],
      "ingredients": [
        "ingredient14",
        "ingredients24"
      ],
      "avatar": "http://z9u1l3wusky40y46t31hrkw2-wpengine.netdna-ssl.com/wp-content/uploads/2016/02/anna-meal-CROP.jpg"
    },
    {
      "id": 4,
      "name": "Meal 555",
      "description": "Its a great meal",
      "favorite": true,
      "steps": [
        "Step15",
        "step25"
      ],
      "ingredients": [
        "ingredient15",
        "ingredients25"
      ],
      "avatar": "https://z9u1l3wusky40y46t31hrkw2-wpengine.netdna-ssl.com/wp-content/uploads/2015/07/Avocado-healthy-foods-to-grill-by-healthista.com_.jpg"
    },
    {
      "id": 5,
      "name": "Meal 666",
      "description": "Its a great meal",
      "favorite": false,
      "steps": [
        "Step16",
        "step26"
      ],
      "ingredients": [
        "ingredient16",
        "ingredients26"
      ],
      "avatar": "https://z9u1l3wusky40y46t31hrkw2-wpengine.netdna-ssl.com/wp-content/uploads/2018/05/glutenfree-healthy-fudge-Brownie-recipe-768.jpg"
    },
    {
      "id": 8,
      "name": "Meal 669",
      "description": "Its a great meal",
      "favorite": false,
      "steps": [
        "Step16",
        "step26"
      ],
      "ingredients": [
        "ingredient16",
        "ingredients26"
      ],
      "avatar": "http://z9u1l3wusky40y46t31hrkw2-wpengine.netdna-ssl.com/wp-content/uploads/2016/03/courgetteandcornfritters-vegetarian-resturaunts-in-london-by-healthista.jpg"
    },
    {
      "name": "name",
      "description": "des",
      "avatar": "ikg",
      "steps": [],
      "ingredients": [],
      "id": 9
    },
    {
      "name": "ssss",
      "description": "sss",
      "avatar": "",
      "steps": [],
      "ingredients": [],
      "id": 10
    },
    {
      "name": "test",
      "description": "test",
      "avatar": "",
      "steps": [],
      "ingredients": [],
      "id": 11
    }
  ]
}
